{
    "general_accumulator": {
        "traffic": {
            "write": 7432972288, 
            "read": 2036414464
        }, 
        "flash_ops": {
            "OP_WRITE": 3793716, 
            "OP_READ": 1161940, 
            "OP_ERASE": 13072
        }, 
        "translation": {
            "read-trans-for-load": 3281, 
            "overwrite-in-cache": 3793716
        }, 
        "channel_busy_time": {
            "channel_6-write-foreground": 90837000000.0, 
            "channel_7-write-foreground": 90790200000.0, 
            "channel_0-write-foreground": 90731200000.0, 
            "channel_1-write-foreground": 90711400000.0, 
            "channel_2-write-foreground": 90719600000.0, 
            "channel_3-write-foreground": 90668000000.0, 
            "channel_4-write-foreground": 90651800000.0, 
            "channel_5-write-foreground": 90767000000.0, 
            "channel_7-read-background": 7640000.0, 
            "channel_0-read-background": 8600000.0, 
            "channel_1-read-background": 7740000.0, 
            "channel_2-read-background": 8380000.0, 
            "channel_4-read-background": 8060000.0, 
            "channel_6-read-background": 8680000.0, 
            "channel_3-read-background": 8800000.0, 
            "channel_5-read-background": 7720000.0, 
            "channel_7-read-foreground": 2458120000.0, 
            "channel_1-read-foreground": 2439640000.0, 
            "channel_6-read-foreground": 2678760000.0, 
            "channel_4-read-foreground": 2514680000.0, 
            "channel_5-read-foreground": 2505280000.0, 
            "channel_2-read-foreground": 2422480000.0, 
            "channel_3-read-foreground": 2429800000.0, 
            "channel_0-read-foreground": 2437720000.0, 
            "channel_0-erase-{'op': 'erase.data.gc', 'op_id': None}": 2452500000.0, 
            "channel_1-erase-{'op': 'erase.data.gc', 'op_id': None}": 2452500000.0, 
            "channel_2-erase-{'op': 'erase.data.gc', 'op_id': None}": 2455500000.0, 
            "channel_3-erase-{'op': 'erase.data.gc', 'op_id': None}": 2445000000.0, 
            "channel_4-erase-{'op': 'erase.data.gc', 'op_id': None}": 2451000000.0, 
            "channel_5-erase-{'op': 'erase.data.gc', 'op_id': None}": 2449500000.0, 
            "channel_6-erase-{'op': 'erase.data.gc', 'op_id': None}": 2448000000.0, 
            "channel_7-erase-{'op': 'erase.data.gc', 'op_id': None}": 2454000000.0, 
            "channel_1-read-{'op': 'read.data.gc', 'op_id': None}": 414680000.0, 
            "channel_0-write-{'op': 'write.data.gc', 'op_id': None}": 4110400000.0, 
            "channel_2-read-{'op': 'read.data.gc', 'op_id': None}": 413440000.0, 
            "channel_2-write-{'op': 'write.data.gc', 'op_id': None}": 4103600000.0, 
            "channel_1-write-{'op': 'write.data.gc', 'op_id': None}": 4107000000.0, 
            "channel_3-write-{'op': 'write.data.gc', 'op_id': None}": 4104800000.0, 
            "channel_3-read-{'op': 'read.data.gc', 'op_id': None}": 395840000.0, 
            "channel_4-write-{'op': 'write.data.gc', 'op_id': None}": 4109800000.0, 
            "channel_5-write-{'op': 'write.data.gc', 'op_id': None}": 4112200000.0, 
            "channel_6-write-{'op': 'write.data.gc', 'op_id': None}": 4107200000.0, 
            "channel_4-read-{'op': 'read.data.gc', 'op_id': None}": 414020000.0, 
            "channel_5-read-{'op': 'read.data.gc', 'op_id': None}": 415780000.0, 
            "channel_7-write-{'op': 'write.data.gc', 'op_id': None}": 4112000000.0, 
            "channel_6-read-{'op': 'read.data.gc', 'op_id': None}": 411980000.0, 
            "channel_7-read-{'op': 'read.data.gc', 'op_id': None}": 408720000.0, 
            "channel_0-read-{'op': 'read.data.gc', 'op_id': None}": 412240000.0
        }, 
        "Mapping_Cache": {
            "miss": 3281, 
            "hit": 4620443
        }, 
        "gc": {
            "erase.data.block": 13072, 
            "user.page.moves": 164335
        }
    }, 
    "clean_func_valid_ratio_snapshot": [
        {
            "0.96": 13, 
            "1.00": 224, 
            "0.99": 8, 
            "0.98": 21, 
            "0.95": 9, 
            "0.88": 3, 
            "0.58": 2, 
            "0.04": 406, 
            "0.02": 390, 
            "0.21": 6, 
            "0.06": 162, 
            "0.05": 371, 
            "0.03": 268, 
            "0.07": 125, 
            "0.00": 71, 
            "0.01": 116, 
            "0.09": 58, 
            "0.08": 73, 
            "0.39": 20, 
            "0.90": 2, 
            "0.94": 11, 
            "0.92": 2, 
            "0.41": 32, 
            "0.50": 16, 
            "0.12": 18, 
            "0.14": 9, 
            "0.10": 14, 
            "0.24": 3, 
            "0.28": 4, 
            "0.51": 13, 
            "0.19": 3, 
            "0.38": 12, 
            "0.32": 4, 
            "0.52": 7, 
            "0.13": 9, 
            "0.66": 3, 
            "0.49": 21, 
            "0.40": 13, 
            "0.35": 4, 
            "0.44": 24, 
            "0.43": 26, 
            "0.36": 12, 
            "0.45": 29, 
            "0.46": 21, 
            "0.42": 14, 
            "0.57": 2, 
            "0.48": 20, 
            "0.47": 18, 
            "0.29": 4, 
            "0.97": 14, 
            "0.85": 1, 
            "0.93": 4, 
            "0.16": 11, 
            "0.67": 1, 
            "0.22": 4, 
            "0.56": 3, 
            "0.11": 16, 
            "0.17": 8, 
            "0.23": 9, 
            "0.15": 6, 
            "0.54": 11, 
            "0.27": 5, 
            "0.55": 4, 
            "0.26": 1, 
            "0.64": 4, 
            "0.80": 1, 
            "0.25": 5, 
            "0.72": 1, 
            "0.30": 5, 
            "0.62": 2, 
            "0.73": 2, 
            "0.18": 3, 
            "0.60": 1, 
            "0.37": 3, 
            "0.34": 4, 
            "0.53": 1, 
            "0.89": 1, 
            "0.87": 2, 
            "0.77": 1, 
            "0.20": 6, 
            "0.59": 1, 
            "0.86": 1, 
            "0.91": 2, 
            "0.31": 2, 
            "0.61": 3, 
            "0.76": 1, 
            "0.33": 2
        }, 
        {
            "0.96": 15, 
            "1.00": 238, 
            "0.99": 12, 
            "0.98": 22, 
            "0.95": 22, 
            "0.88": 4, 
            "0.56": 2, 
            "0.18": 5, 
            "0.06": 251, 
            "0.05": 541, 
            "0.07": 223, 
            "0.09": 75, 
            "0.08": 103, 
            "0.10": 33, 
            "0.14": 22, 
            "0.01": 49, 
            "0.00": 64, 
            "0.03": 154, 
            "0.04": 235, 
            "0.12": 23, 
            "0.20": 11, 
            "0.11": 33, 
            "0.13": 10, 
            "0.02": 204, 
            "0.51": 9, 
            "0.50": 18, 
            "0.33": 6, 
            "0.32": 2, 
            "0.52": 11, 
            "0.39": 23, 
            "0.65": 3, 
            "0.26": 5, 
            "0.97": 28, 
            "0.94": 12, 
            "0.62": 4, 
            "0.61": 7, 
            "0.66": 2, 
            "0.80": 3, 
            "0.21": 6, 
            "0.29": 6, 
            "0.87": 2, 
            "0.34": 4, 
            "0.36": 11, 
            "0.42": 15, 
            "0.40": 11, 
            "0.41": 33, 
            "0.44": 19, 
            "0.54": 8, 
            "0.47": 16, 
            "0.30": 6, 
            "0.43": 22, 
            "0.45": 23, 
            "0.48": 26, 
            "0.49": 17, 
            "0.70": 2, 
            "0.64": 4, 
            "0.57": 5, 
            "0.85": 2, 
            "0.93": 5, 
            "0.16": 4, 
            "0.23": 9, 
            "0.15": 5, 
            "0.17": 6, 
            "0.27": 7, 
            "0.55": 6, 
            "0.91": 4, 
            "0.59": 1, 
            "0.46": 26, 
            "0.38": 11, 
            "0.71": 2, 
            "0.86": 3, 
            "0.92": 6, 
            "0.24": 3, 
            "0.37": 7, 
            "0.60": 2, 
            "0.73": 4, 
            "0.78": 2, 
            "0.89": 2, 
            "0.19": 3, 
            "0.22": 3, 
            "0.67": 1, 
            "0.63": 1, 
            "0.25": 5, 
            "0.84": 1, 
            "0.90": 3, 
            "0.74": 1, 
            "0.35": 4, 
            "0.68": 1, 
            "0.82": 2, 
            "0.69": 1, 
            "0.53": 3, 
            "0.83": 1, 
            "0.28": 1
        }, 
        {
            "0.93": 11, 
            "1.00": 232, 
            "0.99": 10, 
            "0.94": 13, 
            "0.95": 29, 
            "0.88": 6, 
            "0.79": 5, 
            "0.98": 21, 
            "0.56": 1, 
            "0.18": 5, 
            "0.07": 276, 
            "0.06": 327, 
            "0.09": 127, 
            "0.08": 142, 
            "0.10": 43, 
            "0.14": 18, 
            "0.12": 32, 
            "0.17": 9, 
            "0.11": 30, 
            "0.04": 222, 
            "0.05": 226, 
            "0.51": 5, 
            "0.50": 13, 
            "0.29": 6, 
            "0.32": 7, 
            "0.52": 13, 
            "0.39": 21, 
            "0.65": 2, 
            "0.25": 9, 
            "0.63": 2, 
            "0.96": 25, 
            "0.92": 8, 
            "0.59": 6, 
            "0.97": 35, 
            "0.61": 9, 
            "0.66": 2, 
            "0.21": 8, 
            "0.03": 171, 
            "0.87": 3, 
            "0.34": 9, 
            "0.28": 5, 
            "0.02": 218, 
            "0.42": 29, 
            "0.19": 7, 
            "0.01": 63, 
            "0.68": 3, 
            "0.00": 34, 
            "0.15": 8, 
            "0.58": 5, 
            "0.49": 13, 
            "0.41": 28, 
            "0.37": 8, 
            "0.45": 27, 
            "0.46": 24, 
            "0.64": 5, 
            "0.44": 19, 
            "0.55": 9, 
            "0.40": 16, 
            "0.47": 23, 
            "0.43": 22, 
            "0.36": 12, 
            "0.48": 15, 
            "0.38": 12, 
            "0.54": 11, 
            "0.85": 4, 
            "0.80": 4, 
            "0.16": 8, 
            "0.23": 10, 
            "0.27": 6, 
            "0.91": 10, 
            "0.89": 2, 
            "0.60": 2, 
            "0.81": 1, 
            "0.20": 7, 
            "0.71": 1, 
            "0.35": 4, 
            "0.22": 3, 
            "0.13": 7, 
            "0.57": 5, 
            "0.30": 2, 
            "0.83": 1, 
            "0.62": 1, 
            "0.73": 4, 
            "0.78": 2, 
            "0.33": 5, 
            "0.74": 2, 
            "0.82": 3, 
            "0.77": 1, 
            "0.26": 2, 
            "0.84": 1, 
            "0.75": 1, 
            "0.31": 4, 
            "0.86": 2, 
            "0.69": 1, 
            "0.53": 2, 
            "0.24": 2, 
            "0.90": 2, 
            "0.70": 1
        }, 
        {
            "0.93": 14, 
            "1.00": 202, 
            "0.99": 12, 
            "0.94": 15, 
            "0.95": 25, 
            "0.88": 12, 
            "0.77": 5, 
            "0.84": 4, 
            "0.86": 8, 
            "0.96": 26, 
            "0.98": 18, 
            "0.56": 14, 
            "0.17": 6, 
            "0.07": 280, 
            "0.09": 166, 
            "0.08": 189, 
            "0.10": 42, 
            "0.14": 20, 
            "0.12": 29, 
            "0.11": 39, 
            "0.41": 15, 
            "0.39": 24, 
            "0.06": 113, 
            "0.20": 10, 
            "0.45": 33, 
            "0.38": 11, 
            "0.65": 4, 
            "0.25": 8, 
            "0.63": 7, 
            "0.92": 17, 
            "0.50": 26, 
            "0.57": 15, 
            "0.97": 29, 
            "0.61": 10, 
            "0.66": 6, 
            "0.67": 3, 
            "0.21": 10, 
            "0.13": 14, 
            "0.82": 6, 
            "0.34": 10, 
            "0.27": 4, 
            "0.16": 12, 
            "0.32": 5, 
            "0.68": 4, 
            "0.04": 208, 
            "0.05": 240, 
            "0.43": 22, 
            "0.03": 151, 
            "0.01": 66, 
            "0.00": 45, 
            "0.02": 208, 
            "0.40": 9, 
            "0.46": 23, 
            "0.53": 17, 
            "0.54": 27, 
            "0.52": 27, 
            "0.60": 6, 
            "0.29": 12, 
            "0.36": 8, 
            "0.47": 13, 
            "0.37": 7, 
            "0.44": 20, 
            "0.48": 36, 
            "0.49": 24, 
            "0.59": 8, 
            "0.55": 21, 
            "0.85": 6, 
            "0.78": 3, 
            "0.15": 10, 
            "0.33": 6, 
            "0.23": 11, 
            "0.26": 2, 
            "0.90": 6, 
            "0.62": 3, 
            "0.22": 3, 
            "0.35": 5, 
            "0.80": 3, 
            "0.42": 15, 
            "0.89": 3, 
            "0.58": 5, 
            "0.91": 9, 
            "0.81": 2, 
            "0.64": 6, 
            "0.31": 4, 
            "0.24": 4, 
            "0.18": 5, 
            "0.19": 7, 
            "0.75": 2, 
            "0.30": 2, 
            "0.76": 1, 
            "0.72": 2, 
            "0.73": 4, 
            "0.71": 3, 
            "0.51": 7, 
            "0.87": 2, 
            "0.28": 2, 
            "0.70": 1, 
            "0.83": 1, 
            "0.69": 1, 
            "0.79": 1, 
            "0.74": 1
        }, 
        {
            "0.93": 19, 
            "1.00": 176, 
            "0.99": 7, 
            "0.94": 12, 
            "0.95": 29, 
            "0.88": 10, 
            "0.77": 5, 
            "0.82": 8, 
            "0.79": 4, 
            "0.86": 10, 
            "0.87": 6, 
            "0.76": 1, 
            "0.91": 22, 
            "0.98": 14, 
            "0.56": 12, 
            "0.15": 17, 
            "0.09": 182, 
            "0.10": 49, 
            "0.14": 36, 
            "0.08": 198, 
            "0.11": 56, 
            "0.07": 104, 
            "0.12": 39, 
            "0.41": 33, 
            "0.39": 21, 
            "0.20": 21, 
            "0.45": 30, 
            "0.38": 22, 
            "0.65": 8, 
            "0.25": 12, 
            "0.63": 7, 
            "0.50": 26, 
            "0.57": 16, 
            "0.97": 26, 
            "0.61": 10, 
            "0.67": 5, 
            "0.21": 11, 
            "0.13": 17, 
            "0.80": 4, 
            "0.34": 15, 
            "0.23": 19, 
            "0.18": 12, 
            "0.04": 187, 
            "0.32": 9, 
            "0.96": 25, 
            "0.68": 8, 
            "0.03": 154, 
            "0.40": 16, 
            "0.46": 33, 
            "0.52": 38, 
            "0.53": 8, 
            "0.55": 24, 
            "0.51": 21, 
            "0.60": 13, 
            "0.06": 88, 
            "0.81": 5, 
            "0.28": 10, 
            "0.05": 198, 
            "0.02": 227, 
            "0.01": 57, 
            "0.58": 12, 
            "0.69": 6, 
            "0.62": 10, 
            "0.54": 19, 
            "0.00": 33, 
            "0.16": 10, 
            "0.30": 4, 
            "0.36": 12, 
            "0.31": 13, 
            "0.35": 9, 
            "0.24": 6, 
            "0.26": 5, 
            "0.29": 12, 
            "0.49": 21, 
            "0.43": 23, 
            "0.44": 21, 
            "0.42": 14, 
            "0.48": 29, 
            "0.47": 18, 
            "0.37": 11, 
            "0.85": 8, 
            "0.78": 4, 
            "0.84": 4, 
            "0.33": 8, 
            "0.90": 6, 
            "0.22": 10, 
            "0.19": 11, 
            "0.92": 10, 
            "0.89": 6, 
            "0.70": 4, 
            "0.59": 7, 
            "0.17": 10, 
            "0.71": 3, 
            "0.64": 7, 
            "0.75": 4, 
            "0.66": 10, 
            "0.73": 4, 
            "0.27": 6, 
            "0.72": 2, 
            "0.74": 1, 
            "0.83": 3
        }, 
        {
            "0.93": 27, 
            "1.00": 177, 
            "0.99": 10, 
            "0.94": 17, 
            "0.95": 38, 
            "0.88": 10, 
            "0.77": 9, 
            "0.47": 28, 
            "0.70": 4, 
            "0.86": 6, 
            "0.87": 4, 
            "0.76": 3, 
            "0.91": 34, 
            "0.98": 27, 
            "0.56": 9, 
            "0.12": 52, 
            "0.09": 162, 
            "0.10": 68, 
            "0.14": 37, 
            "0.11": 59, 
            "0.35": 12, 
            "0.23": 20, 
            "0.38": 20, 
            "0.37": 12, 
            "0.65": 7, 
            "0.25": 13, 
            "0.63": 6, 
            "0.49": 26, 
            "0.05": 206, 
            "0.74": 5, 
            "0.64": 16, 
            "0.66": 15, 
            "0.21": 12, 
            "0.13": 14, 
            "0.29": 10, 
            "0.15": 20, 
            "0.32": 8, 
            "0.97": 27, 
            "0.96": 27, 
            "0.92": 21, 
            "0.68": 9, 
            "0.08": 60, 
            "0.07": 103, 
            "0.20": 15, 
            "0.40": 14, 
            "0.46": 27, 
            "0.52": 31, 
            "0.53": 17, 
            "0.55": 25, 
            "0.51": 22, 
            "0.50": 27, 
            "0.59": 14, 
            "0.54": 22, 
            "0.60": 13, 
            "0.26": 7, 
            "0.06": 94, 
            "0.57": 22, 
            "0.67": 6, 
            "0.62": 17, 
            "0.61": 9, 
            "0.28": 9, 
            "0.34": 13, 
            "0.36": 11, 
            "0.31": 11, 
            "0.22": 11, 
            "0.41": 22, 
            "0.02": 208, 
            "0.04": 171, 
            "0.00": 47, 
            "0.01": 67, 
            "0.03": 152, 
            "0.33": 7, 
            "0.89": 6, 
            "0.79": 5, 
            "0.17": 6, 
            "0.16": 15, 
            "0.45": 35, 
            "0.42": 21, 
            "0.39": 22, 
            "0.43": 22, 
            "0.48": 45, 
            "0.18": 16, 
            "0.44": 15, 
            "0.27": 9, 
            "0.85": 6, 
            "0.78": 2, 
            "0.84": 5, 
            "0.69": 1, 
            "0.75": 3, 
            "0.19": 6, 
            "0.24": 7, 
            "0.58": 12, 
            "0.83": 5, 
            "0.72": 5, 
            "0.81": 1, 
            "0.71": 6, 
            "0.30": 10, 
            "0.80": 4, 
            "0.82": 7, 
            "0.73": 3, 
            "0.90": 7
        }, 
        {
            "0.93": 32, 
            "1.00": 201, 
            "0.99": 17, 
            "0.94": 25, 
            "0.95": 40, 
            "0.88": 23, 
            "0.77": 9, 
            "0.28": 10, 
            "0.70": 2, 
            "0.86": 11, 
            "0.87": 7, 
            "0.76": 2, 
            "0.91": 31, 
            "0.98": 47, 
            "0.55": 28, 
            "0.12": 46, 
            "0.10": 54, 
            "0.05": 192, 
            "0.09": 59, 
            "0.35": 20, 
            "0.23": 17, 
            "0.14": 28, 
            "0.38": 11, 
            "0.37": 15, 
            "0.65": 4, 
            "0.25": 12, 
            "0.63": 4, 
            "0.49": 25, 
            "0.00": 76, 
            "0.18": 12, 
            "0.11": 77, 
            "0.64": 16, 
            "0.66": 15, 
            "0.03": 152, 
            "0.07": 100, 
            "0.06": 91, 
            "0.32": 13, 
            "0.97": 26, 
            "0.96": 36, 
            "0.68": 10, 
            "0.19": 12, 
            "0.39": 27, 
            "0.45": 37, 
            "0.52": 33, 
            "0.53": 14, 
            "0.54": 21, 
            "0.51": 24, 
            "0.50": 26, 
            "0.58": 10, 
            "0.60": 8, 
            "0.26": 9, 
            "0.20": 13, 
            "0.59": 15, 
            "0.57": 15, 
            "0.62": 16, 
            "0.13": 18, 
            "0.08": 40, 
            "0.17": 9, 
            "0.34": 14, 
            "0.30": 10, 
            "0.24": 11, 
            "0.33": 8, 
            "0.22": 13, 
            "0.90": 16, 
            "0.89": 13, 
            "0.85": 10, 
            "0.84": 4, 
            "0.78": 5, 
            "0.16": 20, 
            "0.15": 11, 
            "0.02": 194, 
            "0.04": 187, 
            "0.01": 72, 
            "0.42": 27, 
            "0.29": 15, 
            "0.48": 48, 
            "0.46": 33, 
            "0.44": 16, 
            "0.31": 4, 
            "0.40": 10, 
            "0.41": 22, 
            "0.43": 18, 
            "0.56": 8, 
            "0.47": 20, 
            "0.69": 2, 
            "0.92": 19, 
            "0.36": 14, 
            "0.67": 2, 
            "0.21": 14, 
            "0.27": 9, 
            "0.82": 8, 
            "0.83": 5, 
            "0.79": 5, 
            "0.71": 6, 
            "0.81": 2, 
            "0.80": 9, 
            "0.73": 3, 
            "0.72": 4, 
            "0.61": 9, 
            "0.75": 1, 
            "0.74": 4
        }, 
        {
            "0.93": 31, 
            "1.00": 203, 
            "0.99": 12, 
            "0.92": 29, 
            "0.95": 60, 
            "0.88": 23, 
            "0.77": 7, 
            "0.22": 14, 
            "0.70": 3, 
            "0.86": 9, 
            "0.87": 12, 
            "0.76": 2, 
            "0.91": 34, 
            "0.98": 40, 
            "0.54": 21, 
            "0.12": 51, 
            "0.35": 13, 
            "0.23": 19, 
            "0.14": 28, 
            "0.38": 17, 
            "0.37": 8, 
            "0.65": 7, 
            "0.25": 15, 
            "0.62": 12, 
            "0.49": 23, 
            "0.06": 94, 
            "0.64": 14, 
            "0.66": 13, 
            "0.32": 8, 
            "0.97": 35, 
            "0.94": 27, 
            "0.96": 48, 
            "0.68": 9, 
            "0.19": 12, 
            "0.39": 27, 
            "0.45": 43, 
            "0.52": 39, 
            "0.53": 20, 
            "0.55": 25, 
            "0.51": 21, 
            "0.50": 33, 
            "0.58": 12, 
            "0.59": 13, 
            "0.90": 13, 
            "0.26": 9, 
            "0.20": 17, 
            "0.57": 14, 
            "0.60": 15, 
            "0.13": 23, 
            "0.17": 8, 
            "0.34": 20, 
            "0.30": 11, 
            "0.24": 11, 
            "0.33": 10, 
            "0.89": 16, 
            "0.21": 14, 
            "0.85": 9, 
            "0.84": 5, 
            "0.78": 7, 
            "0.16": 18, 
            "0.11": 25, 
            "0.73": 4, 
            "0.80": 8, 
            "0.09": 40, 
            "0.04": 235, 
            "0.15": 16, 
            "0.29": 15, 
            "0.41": 19, 
            "0.05": 216, 
            "0.02": 209, 
            "0.00": 42, 
            "0.03": 151, 
            "0.08": 41, 
            "0.01": 50, 
            "0.07": 107, 
            "0.10": 13, 
            "0.47": 31, 
            "0.48": 27, 
            "0.44": 19, 
            "0.36": 14, 
            "0.43": 24, 
            "0.42": 16, 
            "0.46": 33, 
            "0.40": 12, 
            "0.69": 4, 
            "0.82": 12, 
            "0.67": 3, 
            "0.27": 9, 
            "0.28": 6, 
            "0.83": 7, 
            "0.18": 8, 
            "0.56": 7, 
            "0.81": 3, 
            "0.71": 7, 
            "0.74": 4, 
            "0.72": 6, 
            "0.75": 2, 
            "0.61": 6, 
            "0.31": 5, 
            "0.79": 4, 
            "0.63": 2
        }, 
        {
            "0.93": 42, 
            "1.00": 199, 
            "0.99": 14, 
            "0.92": 42, 
            "0.95": 56, 
            "0.88": 28, 
            "0.77": 11, 
            "0.11": 67, 
            "0.70": 8, 
            "0.86": 13, 
            "0.87": 12, 
            "0.76": 2, 
            "0.91": 35, 
            "0.98": 31, 
            "0.53": 16, 
            "0.35": 10, 
            "0.23": 24, 
            "0.14": 80, 
            "0.38": 31, 
            "0.36": 19, 
            "0.65": 7, 
            "0.24": 18, 
            "0.62": 10, 
            "0.49": 27, 
            "0.61": 12, 
            "0.66": 18, 
            "0.32": 11, 
            "0.97": 31, 
            "0.96": 46, 
            "0.94": 33, 
            "0.68": 13, 
            "0.19": 26, 
            "0.39": 26, 
            "0.45": 44, 
            "0.52": 33, 
            "0.54": 19, 
            "0.55": 21, 
            "0.51": 23, 
            "0.50": 31, 
            "0.58": 10, 
            "0.59": 17, 
            "0.48": 30, 
            "0.90": 17, 
            "0.26": 15, 
            "0.20": 36, 
            "0.57": 16, 
            "0.60": 14, 
            "0.17": 33, 
            "0.12": 79, 
            "0.27": 7, 
            "0.22": 15, 
            "0.25": 14, 
            "0.85": 13, 
            "0.84": 13, 
            "0.81": 7, 
            "0.04": 132, 
            "0.71": 8, 
            "0.79": 8, 
            "0.09": 64, 
            "0.07": 78, 
            "0.06": 57, 
            "0.05": 106, 
            "0.15": 37, 
            "0.64": 11, 
            "0.00": 25, 
            "0.40": 19, 
            "0.89": 15, 
            "0.82": 18, 
            "0.08": 43, 
            "0.01": 42, 
            "0.02": 124, 
            "0.10": 31, 
            "0.03": 85, 
            "0.31": 6, 
            "0.18": 37, 
            "0.46": 30, 
            "0.80": 9, 
            "0.29": 11, 
            "0.16": 60, 
            "0.13": 52, 
            "0.47": 17, 
            "0.63": 8, 
            "0.44": 21, 
            "0.30": 9, 
            "0.41": 32, 
            "0.43": 29, 
            "0.37": 6, 
            "0.42": 16, 
            "0.78": 6, 
            "0.69": 3, 
            "0.67": 3, 
            "0.56": 18, 
            "0.21": 19, 
            "0.28": 5, 
            "0.33": 8, 
            "0.34": 11, 
            "0.75": 5, 
            "0.74": 5, 
            "0.73": 4, 
            "0.72": 5, 
            "0.83": 5
        }, 
        {
            "0.93": 56, 
            "1.00": 201, 
            "0.99": 17, 
            "0.92": 36, 
            "0.95": 72, 
            "0.88": 26, 
            "0.77": 14, 
            "0.70": 10, 
            "0.86": 23, 
            "0.87": 14, 
            "0.76": 3, 
            "0.91": 53, 
            "0.98": 41, 
            "0.51": 23, 
            "0.35": 12, 
            "0.38": 22, 
            "0.36": 17, 
            "0.65": 10, 
            "0.62": 18, 
            "0.49": 24, 
            "0.61": 16, 
            "0.66": 22, 
            "0.32": 17, 
            "0.97": 43, 
            "0.96": 63, 
            "0.94": 41, 
            "0.68": 14, 
            "0.39": 20, 
            "0.45": 26, 
            "0.52": 33, 
            "0.53": 18, 
            "0.54": 21, 
            "0.55": 20, 
            "0.50": 40, 
            "0.58": 12, 
            "0.59": 14, 
            "0.48": 29, 
            "0.90": 18, 
            "0.26": 11, 
            "0.57": 17, 
            "0.60": 14, 
            "0.23": 10, 
            "0.20": 4, 
            "0.37": 11, 
            "0.89": 16, 
            "0.84": 13, 
            "0.71": 9, 
            "0.79": 11, 
            "0.21": 5, 
            "0.78": 8, 
            "0.31": 9, 
            "0.69": 4, 
            "0.46": 28, 
            "0.80": 10, 
            "0.34": 12, 
            "0.08": 35, 
            "0.63": 7, 
            "0.44": 16, 
            "0.05": 203, 
            "0.01": 61, 
            "0.02": 215, 
            "0.07": 88, 
            "0.03": 164, 
            "0.04": 216, 
            "0.00": 61, 
            "0.06": 101, 
            "0.09": 35, 
            "0.42": 15, 
            "0.19": 2, 
            "0.47": 26, 
            "0.41": 27, 
            "0.29": 9, 
            "0.43": 31, 
            "0.40": 19, 
            "0.82": 15, 
            "0.85": 13, 
            "0.30": 5, 
            "0.25": 16, 
            "0.67": 5, 
            "0.64": 13, 
            "0.56": 13, 
            "0.81": 11, 
            "0.75": 4, 
            "0.16": 8, 
            "0.11": 13, 
            "0.18": 6, 
            "0.10": 11, 
            "0.13": 4, 
            "0.27": 8, 
            "0.22": 2, 
            "0.17": 1, 
            "0.73": 5, 
            "0.28": 5, 
            "0.33": 4, 
            "0.83": 7, 
            "0.74": 4, 
            "0.24": 5, 
            "0.72": 5, 
            "0.14": 2, 
            "0.12": 1
        }
    ], 
    "gc_first_triggered_timestamp": 20.28964, 
    "average_read_latency_per_page (ns)": 60682.79160618542, 
    "average_write_latency_per_page (ns)": 331333.49462971045, 
    "99.99%_read_latency_per_page (ns)": 500000.0, 
    "99.99%_write_latency_per_page (ns)": 1000000.0, 
    "99.9999%_read_latency_per_page (ns)": 4553090.400004294, 
    "99.9999%_write_latency_per_page (ns)": 8424936.449987581, 
    "total_gc_time (ns)": 20136620000.0, 
    "workload_completion_time (ns)": 120821820000.0
}